catplist/__init__.py
catplist/catplist.py
catplist-0.0.6.dist-info/LICENSE
catplist-0.0.6.dist-info/METADATA
catplist-0.0.6.dist-info/WHEEL
catplist-0.0.6.dist-info/entry_points.txt
catplist-0.0.6.dist-info/top_level.txt
catplist-0.0.6.dist-info/RECORD
