Metadata-Version: 2.1
Name: catplist
Version: 0.0.6
Summary: Print apple plist files in a readable and comprehensible way
Home-page: https://github.com/yoshtec/catplist
Author: Yoshtec
Author-email: yoshtec@gmail.com
Keywords: plist,apple,cat,metadata
Classifier: Programming Language :: Python :: 3
Classifier: License :: OSI Approved :: MIT License
Classifier: Environment :: Console
Classifier: Operating System :: POSIX
Classifier: Operating System :: POSIX :: Linux
Classifier: Operating System :: MacOS
Classifier: Operating System :: Microsoft :: Windows
Classifier: Operating System :: OS Independent
Requires-Python: >=3.5
License-File: LICENSE
Requires-Dist: click
Requires-Dist: ruamel.yaml
